{
    "$schema": "https://schema.management.azure.com/schemas/2015-01-01/deploymentTemplate.json#",
    "contentVersion": "1.0.0.0",
    "parameters": {
        "adminUsername": {
            "type": "string",
            "defaultValue": "VITCAdmin"
        },
        "adminPassword": {
            "type": "securestring"
        },
        "domainName": {
            "type": "string",
            "defaultValue": "vitc.osehra.org"
        },
        "vnetName": {
            "type": "string",
            "defaultValue": "VITC-Common"
        },
        "vnetCIDR": {
            "type": "string",
            "defaultValue": "10.0.0.0/16",
            "metadata": {
                "description": "Enter the VNET CIDR you want to create, ex: 10.0.0.0/16."
            }
        },
        "vnetPrimarySubnetPrefix": {
            "type": "string",
            "defaultValue": "10.0.0.0/24",
            "metadata": {
                "description": "Enter the primary subnet prefix you want to create, ex: 10.0.0.0/24."
            }
        },
        "vnetSecondarySubnetPrefix": {
            "type": "string",
            "defaultValue": "10.0.1.0/24",
            "metadata": {
                "description": "Enter the secondary subnet prefix you want to create, ex: 10.0.1.0/24."
            }
        },
        "jumpBoxVmSize": {
            "type": "string",
            "allowedValues": [
                "Standard_D1_v2",
                "Standard_D2_v2",
                "Standard_D3_v2",
                "Standard_D4_v2",
                "Standard_D5_v2",
                "Standard_D11_v2",
                "Standard_D12_v2",
                "Standard_D13_v2",
                "Standard_D14_v2",
                "Standard_D15_v2",
                "Standard_DS1_v2",
                "Standard_DS2_v2",
                "Standard_DS3_v2",
                "Standard_DS4_v2",
                "Standard_DS5_v2",
                "Standard_DS11_v2",
                "Standard_DS12_v2",
                "Standard_DS13_v2",
                "Standard_DS14_v2",
                "Standard_DS15_v2"
            ],
            "defaultValue": "Standard_D2_v2"
        },
        "DCVmSize": {
            "type": "string",
            "allowedValues": [
                "Standard_D1_v2",
                "Standard_D2_v2",
                "Standard_D3_v2",
                "Standard_D4_v2",
                "Standard_D5_v2",
                "Standard_D11_v2",
                "Standard_D12_v2",
                "Standard_D13_v2",
                "Standard_D14_v2",
                "Standard_D15_v2",
                "Standard_DS1_v2",
                "Standard_DS2_v2",
                "Standard_DS3_v2",
                "Standard_DS4_v2",
                "Standard_DS5_v2",
                "Standard_DS11_v2",
                "Standard_DS12_v2",
                "Standard_DS13_v2",
                "Standard_DS14_v2",
                "Standard_DS15_v2"
            ],
            "defaultValue": "Standard_D1_v2"
        },
        "sandboxVnetName": {
            "type": "string",
            "defaultValue": "VITC-Sandbox"
        },
        "sandboxVnetCIDR": {
            "type": "string",
            "defaultValue": "10.7.0.0/24",
            "metadata": {
                "description": "Enter the VNET CIDR you want to create, ex: 10.7.0.0/24."
            }
        },
        "sandboxOrgName": {
            "type": "string",
            "defaultValue": "VITC-Sandbox-Org"
        },
        "sandboxUserFirstName": {
            "type": "string",
            "defaultValue": "VITC"
        },
        "sandboxUserLastName": {
            "type": "string",
            "defaultValue": "Admin"
        },
        "sandboxAdminUsername": {
            "type": "string",
            "defaultValue": "VITCSandboxAdmin",
            "metadata": {
                "description": "Admin User for Windows and Linux Machines"
            }
        },
        "sandboxAdminPassword": {
            "type": "securestring",
            "metadata": {
                "description": "Sandbox Admin Password"
            }
        },
        "sandboxVmSize": {
            "type": "string",
            "allowedValues": [
                "Standard_D1_v2",
                "Standard_D2_v2",
                "Standard_D3_v2",
                "Standard_D4_v2",
                "Standard_D5_v2",
                "Standard_D11_v2",
                "Standard_D12_v2",
                "Standard_D13_v2",
                "Standard_D14_v2",
                "Standard_D15_v2",
                "Standard_DS1_v2",
                "Standard_DS2_v2",
                "Standard_DS3_v2",
                "Standard_DS4_v2",
                "Standard_DS5_v2",
                "Standard_DS11_v2",
                "Standard_DS12_v2",
                "Standard_DS13_v2",
                "Standard_DS14_v2",
                "Standard_DS15_v2"
            ],
            "defaultValue": "Standard_D3_v2"
        }
    },
    "variables": {
        "winVMName": "VITCWinSandbox",
        "linuxVMName": "VITCLinuxSandbox",
        "coreDeployName": "VITCCoreDeploy",
        "secondaryDeployName": "VITCSecondaryDeploy",
        "storageDeployName": "VITCSandboxStorage",
        "vnetDeployName": "VITCSandboxVNet",
        "winDeployName": "VITCSandboxWin",
        "linuxDeployName": "VITCSandboxLinux",
        "primarySandboxSubnetName": "[concat(parameters('sandboxVnetName'), '-Primary')]",
        "domainNameParts": "[split(parameters('domainName'), '.')]",
        "netBiosName": "[toUpper(variables('domainNameParts')[0])]",
        "baseUri": "[deployment().properties.templateLink.uri]",
        "coreDeployURL": "[uri(variables('baseUri'),'../../core-network/core.json')]",
        "secondaryDeployURL": "[uri(variables('baseUri'),'../../core-network/secondary.json')]",
        "peeringDeployURL": "[uri(variables('baseUri'),'../../core-network/peer.json')]",
        "storageSandboxTemplateURL": "[uri(variables('baseUri'),'../../sandbox/storage.json')]",
        "vnetSandboxTemplateURL": "[uri(variables('baseUri'),'../../sandbox/vnet.json')]",
        "winVMSandboxTemplateURL": "[uri(variables('baseUri'),'../../sandbox/windows-vm.json')]",
        "configWinURL": "[uri(variables('baseUri'),'../../../ps-scripts/configureWindows.ps1')]",
        "updateWinGroupURL": "[uri(variables('baseUri'),'../../../ps-scripts/updateWindowsGroup.ps1')]",
        "winWrapperURL": "[uri(variables('baseUri'),'../../../ps-scripts/winWrapper.ps1')]",

        "linuxVMSandboxTemplateURL": "[uri(variables('baseUri'),'../../sandbox/linux-vm.json')]",
        "configLinuxURL": "[uri(variables('baseUri'),'../../../scripts/linuxWrapper.sh')]",

        "dcConfigScriptURL": "[uri(variables('baseUri'),'../../../ps-scripts/configAD.ps1')]",
        "orgConfigScriptURL": "[uri(variables('baseUri'),'../../../ps-scripts/createOrgOU.ps1')]",
        "userConfigScriptURL": "[uri(variables('baseUri'),'../../../ps-scripts/createUserInOU.ps1')]",
        "joinWindowsScriptURL": "[uri(variables('baseUri'),'../../../ps-scripts/joinWindowsToDomain.ps1')]",
        "adWrapperURL": "[uri(variables('baseUri'),'../../../ps-scripts/adWrapper.ps1')]",

        "subnetCIDRParts": "[split(parameters('vnetPrimarySubnetPrefix'), '/')]",
        "subnetIPParts": "[split(variables('subnetCIDRParts')[0], '.')]",
        "dc1IP": "[concat( variables('subnetIPParts')[0], '.', variables('subnetIPParts')[1], '.', variables('subnetIPParts')[2], '.4')]",
        "dc2IP": "[concat( variables('subnetIPParts')[0], '.', variables('subnetIPParts')[1], '.', variables('subnetIPParts')[2], '.5')]",
        "sandboxSubnetCIDRParts": "[split(parameters('sandboxVnetCIDR'), '/')]",
        "sandboxSubnetIPParts": "[split(variables('sandboxSubnetCIDRParts')[0], '.')]",
        "linuxIP": "[concat( variables('sandboxSubnetIPParts')[0], '.', variables('sandboxSubnetIPParts')[1], '.', variables('sandboxSubnetIPParts')[2], '.4')]",
        "winIP": "[concat( variables('sandboxSubnetIPParts')[0], '.', variables('sandboxSubnetIPParts')[1], '.', variables('sandboxSubnetIPParts')[2], '.5')]",
        "adPDCVMName": "[concat(substring(parameters('vnetName'), 0, 6), '-DC1')]"
    },
    "resources": [
        {
            "name": "[variables('coreDeployName')]",
            "type": "Microsoft.Resources/deployments",
            "apiVersion": "2017-05-10",
            "dependsOn": [],
            "properties": {
                "mode": "Incremental",
                "templateLink": {
                    "uri": "[variables('coreDeployURL')]",
                    "contentVersion": "1.0.0.0"
                },
                "parameters": {
                    "vnetName": {
                        "value": "[parameters('vnetName')]"
                    },
                    "vnetCIDR": {
                        "value": "[parameters('vnetCIDR')]"
                    },
                    "vnetPrimarySubnetPrefix": {
                        "value": "[parameters('vnetPrimarySubnetPrefix')]"
                    },
                    "vnetSecondarySubnetPrefix": {
                        "value": "[parameters('vnetSecondarySubnetPrefix')]"
                    },
                    "DCVmSize": {
                        "value": "[parameters('DCVmSize')]"
                    },
                    "adminUsername": {
                        "value": "[parameters('adminUsername')]"
                    },
                    "adminPassword": {
                        "value": "[parameters('adminPassword')]"
                    },
                    "domainName": {
                        "value": "[parameters('domainName')]"
                    }
                }
            }
        },
        {
            "apiVersion": "2015-06-15",
            "type": "Microsoft.Compute/virtualMachines/extensions",
            "name": "[concat(variables('adPDCVMName'), '/config')]",
            "location": "[resourceGroup().location]",
            "dependsOn": [
                "[resourceId('Microsoft.Resources/deployments', variables('coreDeployName'))]"
            ],
            "tags": {
                "displayName": "config-ad"
            },
            "properties": {
                "publisher": "Microsoft.Compute",
                "type": "CustomScriptExtension",
                "typeHandlerVersion": "1.9",
                "autoUpgradeMinorVersion": true,
                "settings": {
                    "fileUris": [
                        "[variables('dcConfigScriptURL')]",
                        "[variables('orgConfigScriptURL')]",
                        "[variables('userConfigScriptURL')]",
                        "[variables('adWrapperURL')]"
                    ],
                    "commandToExecute": "[concat('powershell -ExecutionPolicy Unrestricted -File adWrapper.ps1 \"', parameters('adminUsername'), '\" \"', parameters('adminPassword'), '\" \"', parameters('domainName'), '\" \"', parameters('sandboxOrgName'), '\" \"', parameters('sandboxAdminUsername'), '\" \"', parameters('sandboxAdminPassword'), '\" \"', parameters('sandboxUserFirstName'), '\" \"', parameters('sandboxUserLastName'), '\"')]"
                },
                "protectedSettings": {}
            }
        },
        {
            "name": "[variables('secondaryDeployName')]",
            "type": "Microsoft.Resources/deployments",
            "apiVersion": "2017-05-10",
            "dependsOn": [
                "[resourceId('Microsoft.Resources/deployments', variables('coreDeployName'))]"
            ],
            "properties": {
                "mode": "Incremental",
                "templateLink": {
                    "uri": "[variables('secondaryDeployURL')]",
                    "contentVersion": "1.0.0.0"
                },
                "parameters": {
                    "vnetName": {
                        "value": "[parameters('vnetName')]"
                    },
                    "DCVmSize": {
                        "value": "[parameters('DCVmSize')]"
                    },
                    "jumpBoxVmSize": {
                        "value": "[parameters('jumpBoxVmSize')]"
                    },
                    "vnetPrimarySubnetPrefix": {
                        "value": "[parameters('vnetPrimarySubnetPrefix')]"
                    },
                    "adminUsername": {
                        "value": "[parameters('adminUsername')]"
                    },
                    "adminPassword": {
                        "value": "[parameters('adminPassword')]"
                    },
                    "diagStorageAccountName": {
                        "value": "[reference(variables('coreDeployName')).outputs.storageResourceID.value]"
                    },
                    "domainName": {
                        "value": "[parameters('domainName')]"
                    }
                }
            }
        },
        {
            "name": "[variables('storageDeployName')]",
            "type": "Microsoft.Resources/deployments",
            "apiVersion": "2017-05-10",
            "dependsOn": [
                "[resourceId('Microsoft.Resources/deployments', variables('coreDeployName'))]"
            ],
            "properties": {
                "mode": "Incremental",
                "templateLink": {
                    "uri": "[variables('storageSandboxTemplateURL')]",
                    "contentVersion": "1.0.0.0"
                },
                "parameters": {
                    "vnetName": {
                        "value": "[parameters('vnetName')]"
                    }
                }
            }
        },
        {
            "name": "[variables('vnetDeployName')]",
            "type": "Microsoft.Resources/deployments",
            "apiVersion": "2017-05-10",
            "dependsOn": [
                "[resourceId('Microsoft.Resources/deployments', variables('coreDeployName'))]"
            ],
            "properties": {
                "mode": "Incremental",
                "templateLink": {
                    "uri": "[variables('vnetSandboxTemplateURL')]",
                    "contentVersion": "1.0.0.0"
                },
                "parameters": {
                    "vnetName": {
                        "value": "[parameters('sandboxVnetName')]"
                    },
                    "vnetCIDR": {
                        "value": "[parameters('sandboxVnetCIDR')]"
                    },
                    "dnsServers": {
                        "value": [
                            "[variables('dc1IP')]",
                            "[variables('dc2IP')]"
                        ]
                    },
                    "vnetPeeringCIDR": {
                        "value": "[parameters('vnetCIDR')]"
                    },
                    "vnetPeeringName": {
                        "value": "[parameters('vnetName')]"
                    },
                    "vnetPeeringGroup": {
                        "value": "[resourceGroup().location]"
                    }
                }
            }
        },
        {
            "name": "PeerSandboxToCommon",
            "type": "Microsoft.Resources/deployments",
            "apiVersion": "2017-05-10",
            "dependsOn": [
                "[resourceId('Microsoft.Resources/deployments', variables('vnetDeployName'))]"
            ],
            "properties": {
                "mode": "Incremental",
                "templateLink": {
                    "uri": "[variables('peeringDeployURL')]",
                    "contentVersion": "1.0.0.0"
                },
                "parameters": {
                    "existingLocalVirtualNetworkName": {
                        "value": "[parameters('sandboxVnetName')]"
                    },
                    "existingRemoteVirtualNetworkName": {
                        "value": "[parameters('vnetName')]"
                    },
                    "existingRemoteVirtualNetworkResourceGroupName": {
                        "value": "[resourceGroup().name]"
                    }
                }
            }
        },
        {
            "name": "PeerCommonToSandbox",
            "type": "Microsoft.Resources/deployments",
            "apiVersion": "2017-05-10",
            "dependsOn": [
                "[resourceId('Microsoft.Resources/deployments', variables('vnetDeployName'))]"
            ],
            "properties": {
                "mode": "Incremental",
                "templateLink": {
                    "uri": "[variables('peeringDeployURL')]",
                    "contentVersion": "1.0.0.0"
                },
                "parameters": {
                    "existingLocalVirtualNetworkName": {
                        "value": "[parameters('vnetName')]"
                    },
                    "existingRemoteVirtualNetworkName": {
                        "value": "[parameters('sandboxVnetName')]"
                    },
                    "existingRemoteVirtualNetworkResourceGroupName": {
                        "value": "[resourceGroup().name]"
                    }
                }
            }
        },
        {
            "name": "[variables('winDeployName')]",
            "type": "Microsoft.Resources/deployments",
            "apiVersion": "2017-05-10",
            "dependsOn": [
                "[resourceId('Microsoft.Resources/deployments', variables('vnetDeployName'))]",
                "[resourceId('Microsoft.Resources/deployments', variables('storageDeployName'))]",
                "[resourceId('Microsoft.Resources/deployments', 'PeerSandboxToCommon')]",
                "[resourceId('Microsoft.Resources/deployments', 'PeerCommonToSandbox')]"
            ],
            "properties": {
                "mode": "Incremental",
                "templateLink": {
                    "uri": "[variables('winVMSandboxTemplateURL')]",
                    "contentVersion": "1.0.0.0"
                },
                "parameters": {
                    "subnetRef": {
                        "value": "[concat(reference(variables('vnetDeployName')).outputs.vnetResourceID.value, '/subnets/', variables('primarySandboxSubnetName'))]"
                    },
                    "storageAccountRefID": {
                        "value": "[reference(variables('storageDeployName')).outputs.storageResourceID.value]"
                    },
                    "adminUsername": {
                        "value": "[parameters('sandboxAdminUsername')]"
                    },
                    "adminPassword": {
                        "value": "[parameters('sandboxAdminPassword')]"
                    },
                    "winIP": {
                        "value": "[variables('winIP')]"
                    },
                    "vmSize": {
                        "value": "[parameters('sandboxVmSize')]"
                    },
                    "assignPublicIP": {
                        "value": true
                    }
                }
            }
        },
        {
            "apiVersion": "2015-06-15",
            "type": "Microsoft.Compute/virtualMachines/extensions",
            "name": "[concat(variables('winVMName'), '/configWin')]",
            "location": "[resourceGroup().location]",
            "dependsOn": [
                "[resourceId('Microsoft.Resources/deployments', variables('winDeployName'))]",
                "[concat('Microsoft.Compute/virtualMachines/', variables('adPDCVMName'),'/extensions/config')]"
            ],
            "tags": {
                "displayName": "config-win"
            },
            "properties": {
                "publisher": "Microsoft.Compute",
                "type": "CustomScriptExtension",
                "typeHandlerVersion": "1.9",
                "autoUpgradeMinorVersion": true,
                "settings": {
                    "fileUris": [
                        "[variables('configWinURL')]",
                        "[variables('updateWinGroupURL')]",
                        "[variables('joinWindowsScriptURL')]",
                        "[variables('winWrapperURL')]"
                    ]
                },
                "protectedSettings": {
                    "commandToExecute": "[concat('powershell -ExecutionPolicy Unrestricted -File winWrapperURL.ps1 \"', variables('linuxIP'), '\" \"', variables('netBiosName'), '\" \"', parameters('adminUsername'), '\" \"', parameters('adminPassword'), '\" \"', parameters('sandboxAdminUsername'), '\" \"', parameters('sandboxAdminPassword'), '\" \"', parameters('sandboxOrgName'), '\" \"', parameters('domainName'), '\"')]"
                }
            }
        },
        {
            "name": "[variables('linuxDeployName')]",
            "type": "Microsoft.Resources/deployments",
            "apiVersion": "2017-05-10",
            "dependsOn": [
                "[resourceId('Microsoft.Resources/deployments', variables('vnetDeployName'))]",
                "[resourceId('Microsoft.Resources/deployments', variables('storageDeployName'))]",
                "[resourceId('Microsoft.Resources/deployments', 'PeerSandboxToCommon')]",
                "[resourceId('Microsoft.Resources/deployments', 'PeerCommonToSandbox')]"
            ],
            "properties": {
                "mode": "Incremental",
                "templateLink": {
                    "uri": "[variables('linuxVMSandboxTemplateURL')]",
                    "contentVersion": "1.0.0.0"
                },
                "parameters": {
                    "subnetRef": {
                        "value": "[concat(reference(variables('vnetDeployName')).outputs.vnetResourceID.value, '/subnets/', variables('primarySandboxSubnetName'))]"
                    },
                    "storageAccountRefID": {
                        "value": "[reference(variables('storageDeployName')).outputs.storageResourceID.value]"
                    },
                    "adminUsername": {
                        "value": "[parameters('sandboxAdminUsername')]"
                    },
                    "adminPassword": {
                        "value": "[parameters('sandboxAdminPassword')]"
                    },
                    "linuxIP": {
                        "value": "[variables('linuxIP')]"
                    },
                    "vmSize": {
                        "value": "[parameters('sandboxVmSize')]"
                    }
                }
            }
        },
        {
            "apiVersion": "2015-06-15",
            "type": "Microsoft.Compute/virtualMachines/extensions",
            "name": "[concat(variables('linuxVMName'), '/configLinux')]",
            "location": "[resourceGroup().location]",
            "dependsOn": [
                "[resourceId('Microsoft.Resources/deployments', variables('linuxDeployName'))]",
                "[concat('Microsoft.Compute/virtualMachines/', variables('adPDCVMName'),'/extensions/config')]"
            ],
            "tags": {
                "displayName": "config-linux"
            },
            "properties": {
                "publisher": "Microsoft.Azure.Extensions",
                "type": "CustomScript",
                "typeHandlerVersion": "2.0",
                "autoUpgradeMinorVersion": true,
                "settings": {
                    "fileUris": [
                        "[variables('configLinuxURL')]"
                    ]
                },
                "protectedSettings": {
                    "commandToExecute": "[concat('./linuxWrapper.sh \"', parameters('sandboxOrgName'), '\" \"', parameters('adminPassword'), '\" \"', parameters('domainName'), '\"')]"
                }
            }
        }
    ],
    "outputs": {}
}